MANIFEST.in
README.md
setup.py
krebszones.egg-info/PKG-INFO
krebszones.egg-info/SOURCES.txt
krebszones.egg-info/dependency_links.txt
krebszones.egg-info/entry_points.txt
krebszones.egg-info/requires.txt
krebszones.egg-info/top_level.txt
zones/__init__.py
zones/ovhzone.py