Metadata-Version: 1.1
Name: krebszones
Version: 0.4.2
Summary: Manages DNS Zones via differnt APIs
Home-page: http://krebsco.de/
Author: makefu
Author-email: spam@krebsco.de
License: WTFPL
Download-URL: https://pypi.python.org/pypi/krebs-zones/
Platform: UNKNOWN
Classifier: Intended Audience :: Developers
Classifier: Natural Language :: English
Classifier: Operating System :: POSIX :: Linux
Classifier: Development Status :: 3 - Alpha
Classifier: Programming Language :: Python
Classifier: Programming Language :: Python :: 3
Classifier: Programming Language :: Python :: 3.4
Classifier: Programming Language :: Python :: Implementation :: CPython
